insar_eventnet/__init__.py
insar_eventnet/aievents.py
insar_eventnet/config.py
insar_eventnet/etc.py
insar_eventnet/gui.py
insar_eventnet/hyp3.py
insar_eventnet/inference.py
insar_eventnet/io.py
insar_eventnet/processing.py
insar_eventnet/sarsim.py
insar_eventnet/synthetic_interferogram.py
insar_eventnet/training.py
insar_eventnet-0.1.0.dist-info/LICENSE
insar_eventnet-0.1.0.dist-info/METADATA
insar_eventnet-0.1.0.dist-info/WHEEL
insar_eventnet-0.1.0.dist-info/entry_points.txt
insar_eventnet-0.1.0.dist-info/top_level.txt
insar_eventnet-0.1.0.dist-info/RECORD
