Metadata-Version: 2.1
Name: insar-eventnet
Version: 0.1.0
Summary: A deep learning model that can recognize and mask significant deformation events in InSAR interferograms.
Author-email: Your Name <you@example.com>
License: BSD 3-Clause License
Project-URL: Homepage, https://github.com/asfadmin/AI-Event-Monitoring/tree/main
Classifier: License :: OSI Approved :: BSD License
Classifier: Natural Language :: English
Classifier: Operating System :: OS Independent
Classifier: Programming Language :: Python
Classifier: Programming Language :: Python :: 3.8
Requires-Python: >=3.8
License-File: LICENSE
Requires-Dist: tensorflow
Requires-Dist: numpy
Requires-Dist: geopy
Requires-Dist: matplotlib
Requires-Dist: scipy
Requires-Dist: click
Requires-Dist: astropy
Requires-Dist: gdal
Requires-Dist: flask
Requires-Dist: hyp3-sdk
